lilac/.gitignore
lilac/__init__.py
lilac/auth.py
lilac/batch_utils.py
lilac/batch_utils_test.py
lilac/cli.py
lilac/concepts/__init__.py
lilac/concepts/concept.py
lilac/concepts/concept_test.py
lilac/concepts/db_concept.py
lilac/concepts/db_concept_test.py
lilac/concepts/language-model-reference/concept.json
lilac/concepts/negative-sentiment/concept.json
lilac/concepts/non-english/concept.json
lilac/concepts/positive-sentiment/concept.json
lilac/concepts/profanity/concept.json
lilac/concepts/question/concept.json
lilac/concepts/source-code/concept.json
lilac/concepts/toxicity/concept.json
lilac/config.py
lilac/conftest.py
lilac/data/__init__.py
lilac/data/cluster_titling.py
lilac/data/clustering.py
lilac/data/clustering_test.py
lilac/data/dataset.py
lilac/data/dataset_compute_signal_chain_test.py
lilac/data/dataset_compute_signal_test.py
lilac/data/dataset_config_test.py
lilac/data/dataset_duckdb.py
lilac/data/dataset_export_test.py
lilac/data/dataset_labels_test.py
lilac/data/dataset_load_embedding_test.py
lilac/data/dataset_map_test.py
lilac/data/dataset_project_test.py
lilac/data/dataset_select_groups_test.py
lilac/data/dataset_select_rows_filter_test.py
lilac/data/dataset_select_rows_schema_test.py
lilac/data/dataset_select_rows_search_test.py
lilac/data/dataset_select_rows_sort_test.py
lilac/data/dataset_select_rows_udf_test.py
lilac/data/dataset_stats_test.py
lilac/data/dataset_storage_utils.py
lilac/data/dataset_test.py
lilac/data/dataset_test_utils.py
lilac/data/dataset_utils.py
lilac/data/dataset_utils_test.py
lilac/dataset_format.py
lilac/dataset_format_test.py
lilac/db_manager.py
lilac/deploy.py
lilac/embeddings/__init__.py
lilac/embeddings/bge.py
lilac/embeddings/cohere.py
lilac/embeddings/default_vector_stores.py
lilac/embeddings/embedding.py
lilac/embeddings/embedding_test.py
lilac/embeddings/gte.py
lilac/embeddings/jina.py
lilac/embeddings/nomic_embed.py
lilac/embeddings/openai.py
lilac/embeddings/sbert.py
lilac/embeddings/transformer_utils.py
lilac-0.3.9.dist-info/LICENSE
lilac-0.3.9.dist-info/METADATA
lilac-0.3.9.dist-info/WHEEL
lilac-0.3.9.dist-info/entry_points.txt
lilac-0.3.9.dist-info/RECORD
