Metadata-Version: 2.1
Name: lilac
Version: 0.3.9
Summary: Organize unstructured data
Home-page: https://github.com/lilacai/lilac
License: Apache-2.0
Author: Lilac AI Inc.
Author-email: info@lilacml.com
Requires-Python: >=3.9,<4.0
Classifier: License :: OSI Approved :: Apache Software License
Classifier: Programming Language :: Python :: 3
Classifier: Programming Language :: Python :: 3.9
Classifier: Programming Language :: Python :: 3.10
Classifier: Programming Language :: Python :: 3.11
Classifier: Programming Language :: Python :: 3.12
Provides-Extra: all
Provides-Extra: bge
Provides-Extra: cohere
Provides-Extra: embeddings
Provides-Extra: github
Provides-Extra: gmail
Provides-Extra: gte
Provides-Extra: lang-detection
Provides-Extra: langsmith
Provides-Extra: llms
Provides-Extra: nomic
Provides-Extra: openai
Provides-Extra: pii
Provides-Extra: sbert
Provides-Extra: signals
Provides-Extra: sources
Provides-Extra: text-stats
Requires-Dist: FlagEmbedding (>=1.2.3,<2.0.0) ; extra == "all" or extra == "bge"
Requires-Dist: authlib (>=1.2.1,<2.0.0)
Requires-Dist: click (>=8.1.3,<9.0.0)
Requires-Dist: cloudpickle (>=2.0.0,<3.0.0)
Requires-Dist: cohere (>=4.32,<5.0) ; extra == "all" or extra == "embeddings" or extra == "cohere"
Requires-Dist: datasets (>=2.12.0,<3.0.0)
Requires-Dist: detect-secrets (>=1.4.0,<2.0.0) ; extra == "all" or extra == "signals" or extra == "pii"
Requires-Dist: duckdb (>=0.9.2,<0.10.0)
Requires-Dist: einops (>=0.7.0,<0.8.0) ; extra == "nomic"
Requires-Dist: email-reply-parser (>=0.5.12,<0.6.0) ; extra == "all" or extra == "gmail"
Requires-Dist: fastapi (>=0.109.1,<0.110.0)
Requires-Dist: fsspec (>=2023.9.2,<2024.0.0)
Requires-Dist: gcsfs (>=2023.9.2,<2024.0.0)
Requires-Dist: google-api-python-client (>=2.88.0,<3.0.0) ; extra == "all" or extra == "gmail"
Requires-Dist: google-auth-httplib2 (>=0.1.0,<0.2.0) ; extra == "all" or extra == "gmail"
Requires-Dist: google-auth-oauthlib (>=1.0.0,<2.0.0) ; extra == "all" or extra == "gmail"
Requires-Dist: google-cloud-storage (>=2.5.0,<3.0.0)
Requires-Dist: gunicorn (>=21.2.0,<22.0.0)
Requires-Dist: hdbscan (>=0.8.33,<0.9.0) ; extra == "all" or extra == "signals"
Requires-Dist: hnswlib (>=0.8.0,<0.9.0)
Requires-Dist: httpx (>=0.24.1,<0.25.0)
Requires-Dist: instructor (>=0.4.0,<0.5.0)
Requires-Dist: itsdangerous (>=2.1.2,<3.0.0)
Requires-Dist: jinja2 (>=3.1.3,<4.0.0)
Requires-Dist: joblib (>=1.3.1,<2.0.0)
Requires-Dist: langdetect (>=1.0.9,<2.0.0) ; extra == "all" or extra == "signals" or extra == "lang-detection"
Requires-Dist: langsmith (>=0.0.41,<0.0.42) ; extra == "all" or extra == "sources" or extra == "langsmith"
Requires-Dist: llama-hub (>=0.0.67,<0.0.68) ; (python_version >= "3.9" and python_version < "3.12") and (extra == "all" or extra == "github")
Requires-Dist: llama-index (>=0.10,<0.11) ; (python_version >= "3.9" and python_version < "3.12") and (extra == "all" or extra == "github")
Requires-Dist: loky (>=3.4.1,<4.0.0)
Requires-Dist: modal (>=0.56.4396,<0.57.0)
Requires-Dist: openai (>=1.7.1,<2.0.0) ; extra == "all" or extra == "embeddings" or extra == "llms" or extra == "openai"
Requires-Dist: orjson (>=3.8.10,<4.0.0)
Requires-Dist: pandas (>=2.0,<3.0)
Requires-Dist: pillow (>=10.2.0,<11.0.0)
Requires-Dist: presidio_analyzer (>=2.2,<3.0) ; extra == "all" or extra == "pii"
Requires-Dist: psutil (>=5.9.5,<6.0.0)
Requires-Dist: pyarrow (>=14.0.1,<15.0.0)
Requires-Dist: pydantic (>=2.5.2,<3.0.0)
Requires-Dist: python-dotenv (>=1.0.0,<2.0.0)
Requires-Dist: pyyaml (>=6.0.1,<7.0.0)
Requires-Dist: requests (>=2,<3)
Requires-Dist: scikit-learn (>=1.3.0,<2.0.0)
Requires-Dist: sentence-transformers (>=2.3.1,<3.0.0) ; extra == "all" or extra == "embeddings" or extra == "gte" or extra == "nomic" or extra == "sbert"
Requires-Dist: spacy (>=3.5.1,<4.0.0) ; extra == "all"
Requires-Dist: tenacity (>=8.2.2,<9.0.0)
Requires-Dist: textacy (>=0.13.0,<0.14.0) ; extra == "all" or extra == "signals" or extra == "text-stats"
Requires-Dist: tiktoken (>=0.5.1,<0.6.0)
Requires-Dist: tqdm (>=4.66.1,<5.0.0)
Requires-Dist: transformers (>=4.37.2,<5.0.0) ; extra == "all" or extra == "bge"
Requires-Dist: typing-extensions (==4.9.0)
Requires-Dist: umap-learn (>=0.5.4,<0.6.0) ; extra == "all"
Requires-Dist: uvicorn[standard] (>=0.23.2,<0.24.0)
Project-URL: Repository, https://github.com/lilacai/lilac
